<?xml version="1.0" encoding="UTF-8" ?>
<!DOCTYPE mapper PUBLIC "-//mybatis.org//DTD Mapper 3.0//EN" "http://mybatis.org/dtd/mybatis-3-mapper.dtd" >
<mapper namespace="com.sunmw.paipai.dao.PpOrderHeadMapper" >
  <resultMap id="BaseResultMap" type="com.sunmw.paipai.domain.PpOrderHead" >
    <!--
      WARNING - @mbggenerated
      This element is automatically generated by MyBatis Generator, do not modify.
    -->
    <id column="pp_order_head_id" property="ppOrderHeadId" jdbcType="INTEGER" />
    <result column="seller_crm" property="sellerCrm" jdbcType="VARCHAR" />
    <result column="buyer_name" property="buyerName" jdbcType="VARCHAR" />
    <result column="buyer_uin" property="buyerUin" jdbcType="VARCHAR" />
    <result column="buyer_remark" property="buyerRemark" jdbcType="VARCHAR" />
    <result column="combo_info" property="comboInfo" jdbcType="VARCHAR" />
    <result column="deal_code" property="dealCode" jdbcType="VARCHAR" />
    <result column="deal_desc" property="dealDesc" jdbcType="VARCHAR" />
    <result column="deal_detail_link" property="dealDetailLink" jdbcType="VARCHAR" />
    <result column="deal_note_type" property="dealNoteType" jdbcType="VARCHAR" />
    <result column="deal_note" property="dealNote" jdbcType="VARCHAR" />
    <result column="deal_state" property="dealState" jdbcType="VARCHAR" />
    <result column="deal_state_desc" property="dealStateDesc" jdbcType="VARCHAR" />
    <result column="property_mask" property="propertyMask" jdbcType="VARCHAR" />
    <result column="deal_type" property="dealType" jdbcType="VARCHAR" />
    <result column="deal_type_desc" property="dealTypeDesc" jdbcType="VARCHAR" />
    <result column="deal_pay_type" property="dealPayType" jdbcType="VARCHAR" />
    <result column="deal_pay_type_desc" property="dealPayTypeDesc" jdbcType="VARCHAR" />
    <result column="deal_rate_state" property="dealRateState" jdbcType="VARCHAR" />
    <result column="deal_rate_state_desc" property="dealRateStateDesc" jdbcType="VARCHAR" />
    <result column="create_time" property="createTime" jdbcType="TIMESTAMP" />
    <result column="deal_end_time" property="dealEndTime" jdbcType="TIMESTAMP" />
    <result column="last_update_time" property="lastUpdateTime" jdbcType="TIMESTAMP" />
    <result column="pay_time" property="payTime" jdbcType="TIMESTAMP" />
    <result column="pay_return_time" property="payReturnTime" jdbcType="TIMESTAMP" />
    <result column="recvfee_return_time" property="recvfeeReturnTime" jdbcType="TIMESTAMP" />
    <result column="recvfee_time" property="recvfeeTime" jdbcType="TIMESTAMP" />
    <result column="seller_consignment_time" property="sellerConsignmentTime" jdbcType="TIMESTAMP" />
    <result column="has_invoice" property="hasInvoice" jdbcType="INTEGER" />
    <result column="invoice_content" property="invoiceContent" jdbcType="VARCHAR" />
    <result column="invoice_title" property="invoiceTitle" jdbcType="VARCHAR" />
    <result column="tenpay_code" property="tenpayCode" jdbcType="VARCHAR" />
    <result column="transport_type" property="transportType" jdbcType="VARCHAR" />
    <result column="transport_type_desc" property="transportTypeDesc" jdbcType="VARCHAR" />
    <result column="who_pay_shippingfee" property="whoPayShippingfee" jdbcType="INTEGER" />
    <result column="wuliu_id" property="wuliuId" jdbcType="VARCHAR" />
    <result column="receiver_address" property="receiverAddress" jdbcType="VARCHAR" />
    <result column="receiver_mobile" property="receiverMobile" jdbcType="VARCHAR" />
    <result column="receiver_name" property="receiverName" jdbcType="VARCHAR" />
    <result column="receiver_phone" property="receiverPhone" jdbcType="VARCHAR" />
    <result column="receiver_postcode" property="receiverPostcode" jdbcType="VARCHAR" />
    <result column="seller_recv_refund" property="sellerRecvRefund" jdbcType="DECIMAL" />
    <result column="buyer_recv_refund" property="buyerRecvRefund" jdbcType="DECIMAL" />
    <result column="coupon_fee" property="couponFee" jdbcType="DECIMAL" />
    <result column="deal_pay_fee_point" property="dealPayFeePoint" jdbcType="DECIMAL" />
    <result column="deal_pay_fee_ticket" property="dealPayFeeTicket" jdbcType="DECIMAL" />
    <result column="deal_pay_fee_total" property="dealPayFeeTotal" jdbcType="DECIMAL" />
    <result column="freight" property="freight" jdbcType="DECIMAL" />
    <result column="shippingfee_calc" property="shippingfeeCalc" jdbcType="DECIMAL" />
    <result column="total_cash" property="totalCash" jdbcType="DECIMAL" />
    <result column="seller_name" property="sellerName" jdbcType="VARCHAR" />
    <result column="seller_uin" property="sellerUin" jdbcType="VARCHAR" />
    <result column="expect_arrival_time" property="expectArrivalTime" jdbcType="TIMESTAMP" />
    <result column="store_id" property="storeId" jdbcType="INTEGER" />
    <result column="update_time" property="updateTime" jdbcType="TIMESTAMP" />
    <result column="update_flag" property="updateFlag" jdbcType="VARCHAR" />
  </resultMap>
  <sql id="Example_Where_Clause" >
    <!--
      WARNING - @mbggenerated
      This element is automatically generated by MyBatis Generator, do not modify.
    -->
    <where >
      <foreach collection="oredCriteria" item="criteria" separator="or" >
        <if test="criteria.valid" >
          <trim prefix="(" suffix=")" prefixOverrides="and" >
            <foreach collection="criteria.criteria" item="criterion" >
              <choose >
                <when test="criterion.noValue" >
                  and ${criterion.condition}
                </when>
                <when test="criterion.singleValue" >
                  and ${criterion.condition} #{criterion.value}
                </when>
                <when test="criterion.betweenValue" >
                  and ${criterion.condition} #{criterion.value} and #{criterion.secondValue}
                </when>
                <when test="criterion.listValue" >
                  and ${criterion.condition}
                  <foreach collection="criterion.value" item="listItem" open="(" close=")" separator="," >
                    #{listItem}
                  </foreach>
                </when>
              </choose>
            </foreach>
          </trim>
        </if>
      </foreach>
    </where>
  </sql>
  <sql id="Update_By_Example_Where_Clause" >
    <!--
      WARNING - @mbggenerated
      This element is automatically generated by MyBatis Generator, do not modify.
    -->
    <where >
      <foreach collection="example.oredCriteria" item="criteria" separator="or" >
        <if test="criteria.valid" >
          <trim prefix="(" suffix=")" prefixOverrides="and" >
            <foreach collection="criteria.criteria" item="criterion" >
              <choose >
                <when test="criterion.noValue" >
                  and ${criterion.condition}
                </when>
                <when test="criterion.singleValue" >
                  and ${criterion.condition} #{criterion.value}
                </when>
                <when test="criterion.betweenValue" >
                  and ${criterion.condition} #{criterion.value} and #{criterion.secondValue}
                </when>
                <when test="criterion.listValue" >
                  and ${criterion.condition}
                  <foreach collection="criterion.value" item="listItem" open="(" close=")" separator="," >
                    #{listItem}
                  </foreach>
                </when>
              </choose>
            </foreach>
          </trim>
        </if>
      </foreach>
    </where>
  </sql>
  <sql id="Base_Column_List" >
    <!--
      WARNING - @mbggenerated
      This element is automatically generated by MyBatis Generator, do not modify.
    -->
    pp_order_head_id, seller_crm, buyer_name, buyer_uin, buyer_remark, combo_info, deal_code, 
    deal_desc, deal_detail_link, deal_note_type, deal_note, deal_state, deal_state_desc, 
    property_mask, deal_type, deal_type_desc, deal_pay_type, deal_pay_type_desc, deal_rate_state, 
    deal_rate_state_desc, create_time, deal_end_time, last_update_time, pay_time, pay_return_time, 
    recvfee_return_time, recvfee_time, seller_consignment_time, has_invoice, invoice_content, 
    invoice_title, tenpay_code, transport_type, transport_type_desc, who_pay_shippingfee, 
    wuliu_id, receiver_address, receiver_mobile, receiver_name, receiver_phone, receiver_postcode, 
    seller_recv_refund, buyer_recv_refund, coupon_fee, deal_pay_fee_point, deal_pay_fee_ticket, 
    deal_pay_fee_total, freight, shippingfee_calc, total_cash, seller_name, seller_uin, 
    expect_arrival_time, store_id, update_time, update_flag
  </sql>
  <select id="selectByExample" resultMap="BaseResultMap" parameterType="com.sunmw.paipai.domain.PpOrderHeadExample" >
    <!--
      WARNING - @mbggenerated
      This element is automatically generated by MyBatis Generator, do not modify.
    -->
    select
    <if test="distinct" >
      distinct
    </if>
    <include refid="Base_Column_List" />
    from pp_order_head
    <if test="_parameter != null" >
      <include refid="Example_Where_Clause" />
    </if>
    <if test="orderByClause != null" >
      order by ${orderByClause}
    </if>
  </select>
  <select id="selectByPrimaryKey" resultMap="BaseResultMap" parameterType="java.lang.Integer" >
    <!--
      WARNING - @mbggenerated
      This element is automatically generated by MyBatis Generator, do not modify.
    -->
    select 
    <include refid="Base_Column_List" />
    from pp_order_head
    where pp_order_head_id = #{ppOrderHeadId,jdbcType=INTEGER}
  </select>
  <delete id="deleteByPrimaryKey" parameterType="java.lang.Integer" >
    <!--
      WARNING - @mbggenerated
      This element is automatically generated by MyBatis Generator, do not modify.
    -->
    delete from pp_order_head
    where pp_order_head_id = #{ppOrderHeadId,jdbcType=INTEGER}
  </delete>
  <delete id="deleteByExample" parameterType="com.sunmw.paipai.domain.PpOrderHeadExample" >
    <!--
      WARNING - @mbggenerated
      This element is automatically generated by MyBatis Generator, do not modify.
    -->
    delete from pp_order_head
    <if test="_parameter != null" >
      <include refid="Example_Where_Clause" />
    </if>
  </delete>
  <insert id="insert" parameterType="com.sunmw.paipai.domain.PpOrderHead" >
    <!--
      WARNING - @mbggenerated
      This element is automatically generated by MyBatis Generator, do not modify.
    -->
    insert into pp_order_head (pp_order_head_id, seller_crm, buyer_name, 
      buyer_uin, buyer_remark, combo_info, 
      deal_code, deal_desc, deal_detail_link, 
      deal_note_type, deal_note, deal_state, 
      deal_state_desc, property_mask, deal_type, 
      deal_type_desc, deal_pay_type, deal_pay_type_desc, 
      deal_rate_state, deal_rate_state_desc, create_time, 
      deal_end_time, last_update_time, pay_time, 
      pay_return_time, recvfee_return_time, recvfee_time, 
      seller_consignment_time, has_invoice, invoice_content, 
      invoice_title, tenpay_code, transport_type, 
      transport_type_desc, who_pay_shippingfee, wuliu_id, 
      receiver_address, receiver_mobile, receiver_name, 
      receiver_phone, receiver_postcode, seller_recv_refund, 
      buyer_recv_refund, coupon_fee, deal_pay_fee_point, 
      deal_pay_fee_ticket, deal_pay_fee_total, freight, 
      shippingfee_calc, total_cash, seller_name, 
      seller_uin, expect_arrival_time, store_id, 
      update_time, update_flag)
    values (#{ppOrderHeadId,jdbcType=INTEGER}, #{sellerCrm,jdbcType=VARCHAR}, #{buyerName,jdbcType=VARCHAR}, 
      #{buyerUin,jdbcType=VARCHAR}, #{buyerRemark,jdbcType=VARCHAR}, #{comboInfo,jdbcType=VARCHAR}, 
      #{dealCode,jdbcType=VARCHAR}, #{dealDesc,jdbcType=VARCHAR}, #{dealDetailLink,jdbcType=VARCHAR}, 
      #{dealNoteType,jdbcType=VARCHAR}, #{dealNote,jdbcType=VARCHAR}, #{dealState,jdbcType=VARCHAR}, 
      #{dealStateDesc,jdbcType=VARCHAR}, #{propertyMask,jdbcType=VARCHAR}, #{dealType,jdbcType=VARCHAR}, 
      #{dealTypeDesc,jdbcType=VARCHAR}, #{dealPayType,jdbcType=VARCHAR}, #{dealPayTypeDesc,jdbcType=VARCHAR}, 
      #{dealRateState,jdbcType=VARCHAR}, #{dealRateStateDesc,jdbcType=VARCHAR}, #{createTime,jdbcType=TIMESTAMP}, 
      #{dealEndTime,jdbcType=TIMESTAMP}, #{lastUpdateTime,jdbcType=TIMESTAMP}, #{payTime,jdbcType=TIMESTAMP}, 
      #{payReturnTime,jdbcType=TIMESTAMP}, #{recvfeeReturnTime,jdbcType=TIMESTAMP}, #{recvfeeTime,jdbcType=TIMESTAMP}, 
      #{sellerConsignmentTime,jdbcType=TIMESTAMP}, #{hasInvoice,jdbcType=INTEGER}, #{invoiceContent,jdbcType=VARCHAR}, 
      #{invoiceTitle,jdbcType=VARCHAR}, #{tenpayCode,jdbcType=VARCHAR}, #{transportType,jdbcType=VARCHAR}, 
      #{transportTypeDesc,jdbcType=VARCHAR}, #{whoPayShippingfee,jdbcType=INTEGER}, #{wuliuId,jdbcType=VARCHAR}, 
      #{receiverAddress,jdbcType=VARCHAR}, #{receiverMobile,jdbcType=VARCHAR}, #{receiverName,jdbcType=VARCHAR}, 
      #{receiverPhone,jdbcType=VARCHAR}, #{receiverPostcode,jdbcType=VARCHAR}, #{sellerRecvRefund,jdbcType=DECIMAL}, 
      #{buyerRecvRefund,jdbcType=DECIMAL}, #{couponFee,jdbcType=DECIMAL}, #{dealPayFeePoint,jdbcType=DECIMAL}, 
      #{dealPayFeeTicket,jdbcType=DECIMAL}, #{dealPayFeeTotal,jdbcType=DECIMAL}, #{freight,jdbcType=DECIMAL}, 
      #{shippingfeeCalc,jdbcType=DECIMAL}, #{totalCash,jdbcType=DECIMAL}, #{sellerName,jdbcType=VARCHAR}, 
      #{sellerUin,jdbcType=VARCHAR}, #{expectArrivalTime,jdbcType=TIMESTAMP}, #{storeId,jdbcType=INTEGER}, 
      #{updateTime,jdbcType=TIMESTAMP}, #{updateFlag,jdbcType=VARCHAR})
  </insert>
  <insert id="insertSelective" parameterType="com.sunmw.paipai.domain.PpOrderHead" >
    <!--
      WARNING - @mbggenerated
      This element is automatically generated by MyBatis Generator, do not modify.
    -->
    insert into pp_order_head
    <trim prefix="(" suffix=")" suffixOverrides="," >
      <if test="ppOrderHeadId != null" >
        pp_order_head_id,
      </if>
      <if test="sellerCrm != null" >
        seller_crm,
      </if>
      <if test="buyerName != null" >
        buyer_name,
      </if>
      <if test="buyerUin != null" >
        buyer_uin,
      </if>
      <if test="buyerRemark != null" >
        buyer_remark,
      </if>
      <if test="comboInfo != null" >
        combo_info,
      </if>
      <if test="dealCode != null" >
        deal_code,
      </if>
      <if test="dealDesc != null" >
        deal_desc,
      </if>
      <if test="dealDetailLink != null" >
        deal_detail_link,
      </if>
      <if test="dealNoteType != null" >
        deal_note_type,
      </if>
      <if test="dealNote != null" >
        deal_note,
      </if>
      <if test="dealState != null" >
        deal_state,
      </if>
      <if test="dealStateDesc != null" >
        deal_state_desc,
      </if>
      <if test="propertyMask != null" >
        property_mask,
      </if>
      <if test="dealType != null" >
        deal_type,
      </if>
      <if test="dealTypeDesc != null" >
        deal_type_desc,
      </if>
      <if test="dealPayType != null" >
        deal_pay_type,
      </if>
      <if test="dealPayTypeDesc != null" >
        deal_pay_type_desc,
      </if>
      <if test="dealRateState != null" >
        deal_rate_state,
      </if>
      <if test="dealRateStateDesc != null" >
        deal_rate_state_desc,
      </if>
      <if test="createTime != null" >
        create_time,
      </if>
      <if test="dealEndTime != null" >
        deal_end_time,
      </if>
      <if test="lastUpdateTime != null" >
        last_update_time,
      </if>
      <if test="payTime != null" >
        pay_time,
      </if>
      <if test="payReturnTime != null" >
        pay_return_time,
      </if>
      <if test="recvfeeReturnTime != null" >
        recvfee_return_time,
      </if>
      <if test="recvfeeTime != null" >
        recvfee_time,
      </if>
      <if test="sellerConsignmentTime != null" >
        seller_consignment_time,
      </if>
      <if test="hasInvoice != null" >
        has_invoice,
      </if>
      <if test="invoiceContent != null" >
        invoice_content,
      </if>
      <if test="invoiceTitle != null" >
        invoice_title,
      </if>
      <if test="tenpayCode != null" >
        tenpay_code,
      </if>
      <if test="transportType != null" >
        transport_type,
      </if>
      <if test="transportTypeDesc != null" >
        transport_type_desc,
      </if>
      <if test="whoPayShippingfee != null" >
        who_pay_shippingfee,
      </if>
      <if test="wuliuId != null" >
        wuliu_id,
      </if>
      <if test="receiverAddress != null" >
        receiver_address,
      </if>
      <if test="receiverMobile != null" >
        receiver_mobile,
      </if>
      <if test="receiverName != null" >
        receiver_name,
      </if>
      <if test="receiverPhone != null" >
        receiver_phone,
      </if>
      <if test="receiverPostcode != null" >
        receiver_postcode,
      </if>
      <if test="sellerRecvRefund != null" >
        seller_recv_refund,
      </if>
      <if test="buyerRecvRefund != null" >
        buyer_recv_refund,
      </if>
      <if test="couponFee != null" >
        coupon_fee,
      </if>
      <if test="dealPayFeePoint != null" >
        deal_pay_fee_point,
      </if>
      <if test="dealPayFeeTicket != null" >
        deal_pay_fee_ticket,
      </if>
      <if test="dealPayFeeTotal != null" >
        deal_pay_fee_total,
      </if>
      <if test="freight != null" >
        freight,
      </if>
      <if test="shippingfeeCalc != null" >
        shippingfee_calc,
      </if>
      <if test="totalCash != null" >
        total_cash,
      </if>
      <if test="sellerName != null" >
        seller_name,
      </if>
      <if test="sellerUin != null" >
        seller_uin,
      </if>
      <if test="expectArrivalTime != null" >
        expect_arrival_time,
      </if>
      <if test="storeId != null" >
        store_id,
      </if>
      <if test="updateTime != null" >
        update_time,
      </if>
      <if test="updateFlag != null" >
        update_flag,
      </if>
    </trim>
    <trim prefix="values (" suffix=")" suffixOverrides="," >
      <if test="ppOrderHeadId != null" >
        #{ppOrderHeadId,jdbcType=INTEGER},
      </if>
      <if test="sellerCrm != null" >
        #{sellerCrm,jdbcType=VARCHAR},
      </if>
      <if test="buyerName != null" >
        #{buyerName,jdbcType=VARCHAR},
      </if>
      <if test="buyerUin != null" >
        #{buyerUin,jdbcType=VARCHAR},
      </if>
      <if test="buyerRemark != null" >
        #{buyerRemark,jdbcType=VARCHAR},
      </if>
      <if test="comboInfo != null" >
        #{comboInfo,jdbcType=VARCHAR},
      </if>
      <if test="dealCode != null" >
        #{dealCode,jdbcType=VARCHAR},
      </if>
      <if test="dealDesc != null" >
        #{dealDesc,jdbcType=VARCHAR},
      </if>
      <if test="dealDetailLink != null" >
        #{dealDetailLink,jdbcType=VARCHAR},
      </if>
      <if test="dealNoteType != null" >
        #{dealNoteType,jdbcType=VARCHAR},
      </if>
      <if test="dealNote != null" >
        #{dealNote,jdbcType=VARCHAR},
      </if>
      <if test="dealState != null" >
        #{dealState,jdbcType=VARCHAR},
      </if>
      <if test="dealStateDesc != null" >
        #{dealStateDesc,jdbcType=VARCHAR},
      </if>
      <if test="propertyMask != null" >
        #{propertyMask,jdbcType=VARCHAR},
      </if>
      <if test="dealType != null" >
        #{dealType,jdbcType=VARCHAR},
      </if>
      <if test="dealTypeDesc != null" >
        #{dealTypeDesc,jdbcType=VARCHAR},
      </if>
      <if test="dealPayType != null" >
        #{dealPayType,jdbcType=VARCHAR},
      </if>
      <if test="dealPayTypeDesc != null" >
        #{dealPayTypeDesc,jdbcType=VARCHAR},
      </if>
      <if test="dealRateState != null" >
        #{dealRateState,jdbcType=VARCHAR},
      </if>
      <if test="dealRateStateDesc != null" >
        #{dealRateStateDesc,jdbcType=VARCHAR},
      </if>
      <if test="createTime != null" >
        #{createTime,jdbcType=TIMESTAMP},
      </if>
      <if test="dealEndTime != null" >
        #{dealEndTime,jdbcType=TIMESTAMP},
      </if>
      <if test="lastUpdateTime != null" >
        #{lastUpdateTime,jdbcType=TIMESTAMP},
      </if>
      <if test="payTime != null" >
        #{payTime,jdbcType=TIMESTAMP},
      </if>
      <if test="payReturnTime != null" >
        #{payReturnTime,jdbcType=TIMESTAMP},
      </if>
      <if test="recvfeeReturnTime != null" >
        #{recvfeeReturnTime,jdbcType=TIMESTAMP},
      </if>
      <if test="recvfeeTime != null" >
        #{recvfeeTime,jdbcType=TIMESTAMP},
      </if>
      <if test="sellerConsignmentTime != null" >
        #{sellerConsignmentTime,jdbcType=TIMESTAMP},
      </if>
      <if test="hasInvoice != null" >
        #{hasInvoice,jdbcType=INTEGER},
      </if>
      <if test="invoiceContent != null" >
        #{invoiceContent,jdbcType=VARCHAR},
      </if>
      <if test="invoiceTitle != null" >
        #{invoiceTitle,jdbcType=VARCHAR},
      </if>
      <if test="tenpayCode != null" >
        #{tenpayCode,jdbcType=VARCHAR},
      </if>
      <if test="transportType != null" >
        #{transportType,jdbcType=VARCHAR},
      </if>
      <if test="transportTypeDesc != null" >
        #{transportTypeDesc,jdbcType=VARCHAR},
      </if>
      <if test="whoPayShippingfee != null" >
        #{whoPayShippingfee,jdbcType=INTEGER},
      </if>
      <if test="wuliuId != null" >
        #{wuliuId,jdbcType=VARCHAR},
      </if>
      <if test="receiverAddress != null" >
        #{receiverAddress,jdbcType=VARCHAR},
      </if>
      <if test="receiverMobile != null" >
        #{receiverMobile,jdbcType=VARCHAR},
      </if>
      <if test="receiverName != null" >
        #{receiverName,jdbcType=VARCHAR},
      </if>
      <if test="receiverPhone != null" >
        #{receiverPhone,jdbcType=VARCHAR},
      </if>
      <if test="receiverPostcode != null" >
        #{receiverPostcode,jdbcType=VARCHAR},
      </if>
      <if test="sellerRecvRefund != null" >
        #{sellerRecvRefund,jdbcType=DECIMAL},
      </if>
      <if test="buyerRecvRefund != null" >
        #{buyerRecvRefund,jdbcType=DECIMAL},
      </if>
      <if test="couponFee != null" >
        #{couponFee,jdbcType=DECIMAL},
      </if>
      <if test="dealPayFeePoint != null" >
        #{dealPayFeePoint,jdbcType=DECIMAL},
      </if>
      <if test="dealPayFeeTicket != null" >
        #{dealPayFeeTicket,jdbcType=DECIMAL},
      </if>
      <if test="dealPayFeeTotal != null" >
        #{dealPayFeeTotal,jdbcType=DECIMAL},
      </if>
      <if test="freight != null" >
        #{freight,jdbcType=DECIMAL},
      </if>
      <if test="shippingfeeCalc != null" >
        #{shippingfeeCalc,jdbcType=DECIMAL},
      </if>
      <if test="totalCash != null" >
        #{totalCash,jdbcType=DECIMAL},
      </if>
      <if test="sellerName != null" >
        #{sellerName,jdbcType=VARCHAR},
      </if>
      <if test="sellerUin != null" >
        #{sellerUin,jdbcType=VARCHAR},
      </if>
      <if test="expectArrivalTime != null" >
        #{expectArrivalTime,jdbcType=TIMESTAMP},
      </if>
      <if test="storeId != null" >
        #{storeId,jdbcType=INTEGER},
      </if>
      <if test="updateTime != null" >
        #{updateTime,jdbcType=TIMESTAMP},
      </if>
      <if test="updateFlag != null" >
        #{updateFlag,jdbcType=VARCHAR},
      </if>
    </trim>
  </insert>
  <select id="countByExample" parameterType="com.sunmw.paipai.domain.PpOrderHeadExample" resultType="java.lang.Integer" >
    <!--
      WARNING - @mbggenerated
      This element is automatically generated by MyBatis Generator, do not modify.
    -->
    select count(*) from pp_order_head
    <if test="_parameter != null" >
      <include refid="Example_Where_Clause" />
    </if>
  </select>
  <update id="updateByExampleSelective" parameterType="map" >
    <!--
      WARNING - @mbggenerated
      This element is automatically generated by MyBatis Generator, do not modify.
    -->
    update pp_order_head
    <set >
      <if test="record.ppOrderHeadId != null" >
        pp_order_head_id = #{record.ppOrderHeadId,jdbcType=INTEGER},
      </if>
      <if test="record.sellerCrm != null" >
        seller_crm = #{record.sellerCrm,jdbcType=VARCHAR},
      </if>
      <if test="record.buyerName != null" >
        buyer_name = #{record.buyerName,jdbcType=VARCHAR},
      </if>
      <if test="record.buyerUin != null" >
        buyer_uin = #{record.buyerUin,jdbcType=VARCHAR},
      </if>
      <if test="record.buyerRemark != null" >
        buyer_remark = #{record.buyerRemark,jdbcType=VARCHAR},
      </if>
      <if test="record.comboInfo != null" >
        combo_info = #{record.comboInfo,jdbcType=VARCHAR},
      </if>
      <if test="record.dealCode != null" >
        deal_code = #{record.dealCode,jdbcType=VARCHAR},
      </if>
      <if test="record.dealDesc != null" >
        deal_desc = #{record.dealDesc,jdbcType=VARCHAR},
      </if>
      <if test="record.dealDetailLink != null" >
        deal_detail_link = #{record.dealDetailLink,jdbcType=VARCHAR},
      </if>
      <if test="record.dealNoteType != null" >
        deal_note_type = #{record.dealNoteType,jdbcType=VARCHAR},
      </if>
      <if test="record.dealNote != null" >
        deal_note = #{record.dealNote,jdbcType=VARCHAR},
      </if>
      <if test="record.dealState != null" >
        deal_state = #{record.dealState,jdbcType=VARCHAR},
      </if>
      <if test="record.dealStateDesc != null" >
        deal_state_desc = #{record.dealStateDesc,jdbcType=VARCHAR},
      </if>
      <if test="record.propertyMask != null" >
        property_mask = #{record.propertyMask,jdbcType=VARCHAR},
      </if>
      <if test="record.dealType != null" >
        deal_type = #{record.dealType,jdbcType=VARCHAR},
      </if>
      <if test="record.dealTypeDesc != null" >
        deal_type_desc = #{record.dealTypeDesc,jdbcType=VARCHAR},
      </if>
      <if test="record.dealPayType != null" >
        deal_pay_type = #{record.dealPayType,jdbcType=VARCHAR},
      </if>
      <if test="record.dealPayTypeDesc != null" >
        deal_pay_type_desc = #{record.dealPayTypeDesc,jdbcType=VARCHAR},
      </if>
      <if test="record.dealRateState != null" >
        deal_rate_state = #{record.dealRateState,jdbcType=VARCHAR},
      </if>
      <if test="record.dealRateStateDesc != null" >
        deal_rate_state_desc = #{record.dealRateStateDesc,jdbcType=VARCHAR},
      </if>
      <if test="record.createTime != null" >
        create_time = #{record.createTime,jdbcType=TIMESTAMP},
      </if>
      <if test="record.dealEndTime != null" >
        deal_end_time = #{record.dealEndTime,jdbcType=TIMESTAMP},
      </if>
      <if test="record.lastUpdateTime != null" >
        last_update_time = #{record.lastUpdateTime,jdbcType=TIMESTAMP},
      </if>
      <if test="record.payTime != null" >
        pay_time = #{record.payTime,jdbcType=TIMESTAMP},
      </if>
      <if test="record.payReturnTime != null" >
        pay_return_time = #{record.payReturnTime,jdbcType=TIMESTAMP},
      </if>
      <if test="record.recvfeeReturnTime != null" >
        recvfee_return_time = #{record.recvfeeReturnTime,jdbcType=TIMESTAMP},
      </if>
      <if test="record.recvfeeTime != null" >
        recvfee_time = #{record.recvfeeTime,jdbcType=TIMESTAMP},
      </if>
      <if test="record.sellerConsignmentTime != null" >
        seller_consignment_time = #{record.sellerConsignmentTime,jdbcType=TIMESTAMP},
      </if>
      <if test="record.hasInvoice != null" >
        has_invoice = #{record.hasInvoice,jdbcType=INTEGER},
      </if>
      <if test="record.invoiceContent != null" >
        invoice_content = #{record.invoiceContent,jdbcType=VARCHAR},
      </if>
      <if test="record.invoiceTitle != null" >
        invoice_title = #{record.invoiceTitle,jdbcType=VARCHAR},
      </if>
      <if test="record.tenpayCode != null" >
        tenpay_code = #{record.tenpayCode,jdbcType=VARCHAR},
      </if>
      <if test="record.transportType != null" >
        transport_type = #{record.transportType,jdbcType=VARCHAR},
      </if>
      <if test="record.transportTypeDesc != null" >
        transport_type_desc = #{record.transportTypeDesc,jdbcType=VARCHAR},
      </if>
      <if test="record.whoPayShippingfee != null" >
        who_pay_shippingfee = #{record.whoPayShippingfee,jdbcType=INTEGER},
      </if>
      <if test="record.wuliuId != null" >
        wuliu_id = #{record.wuliuId,jdbcType=VARCHAR},
      </if>
      <if test="record.receiverAddress != null" >
        receiver_address = #{record.receiverAddress,jdbcType=VARCHAR},
      </if>
      <if test="record.receiverMobile != null" >
        receiver_mobile = #{record.receiverMobile,jdbcType=VARCHAR},
      </if>
      <if test="record.receiverName != null" >
        receiver_name = #{record.receiverName,jdbcType=VARCHAR},
      </if>
      <if test="record.receiverPhone != null" >
        receiver_phone = #{record.receiverPhone,jdbcType=VARCHAR},
      </if>
      <if test="record.receiverPostcode != null" >
        receiver_postcode = #{record.receiverPostcode,jdbcType=VARCHAR},
      </if>
      <if test="record.sellerRecvRefund != null" >
        seller_recv_refund = #{record.sellerRecvRefund,jdbcType=DECIMAL},
      </if>
      <if test="record.buyerRecvRefund != null" >
        buyer_recv_refund = #{record.buyerRecvRefund,jdbcType=DECIMAL},
      </if>
      <if test="record.couponFee != null" >
        coupon_fee = #{record.couponFee,jdbcType=DECIMAL},
      </if>
      <if test="record.dealPayFeePoint != null" >
        deal_pay_fee_point = #{record.dealPayFeePoint,jdbcType=DECIMAL},
      </if>
      <if test="record.dealPayFeeTicket != null" >
        deal_pay_fee_ticket = #{record.dealPayFeeTicket,jdbcType=DECIMAL},
      </if>
      <if test="record.dealPayFeeTotal != null" >
        deal_pay_fee_total = #{record.dealPayFeeTotal,jdbcType=DECIMAL},
      </if>
      <if test="record.freight != null" >
        freight = #{record.freight,jdbcType=DECIMAL},
      </if>
      <if test="record.shippingfeeCalc != null" >
        shippingfee_calc = #{record.shippingfeeCalc,jdbcType=DECIMAL},
      </if>
      <if test="record.totalCash != null" >
        total_cash = #{record.totalCash,jdbcType=DECIMAL},
      </if>
      <if test="record.sellerName != null" >
        seller_name = #{record.sellerName,jdbcType=VARCHAR},
      </if>
      <if test="record.sellerUin != null" >
        seller_uin = #{record.sellerUin,jdbcType=VARCHAR},
      </if>
      <if test="record.expectArrivalTime != null" >
        expect_arrival_time = #{record.expectArrivalTime,jdbcType=TIMESTAMP},
      </if>
      <if test="record.storeId != null" >
        store_id = #{record.storeId,jdbcType=INTEGER},
      </if>
      <if test="record.updateTime != null" >
        update_time = #{record.updateTime,jdbcType=TIMESTAMP},
      </if>
      <if test="record.updateFlag != null" >
        update_flag = #{record.updateFlag,jdbcType=VARCHAR},
      </if>
    </set>
    <if test="_parameter != null" >
      <include refid="Update_By_Example_Where_Clause" />
    </if>
  </update>
  <update id="updateByExample" parameterType="map" >
    <!--
      WARNING - @mbggenerated
      This element is automatically generated by MyBatis Generator, do not modify.
    -->
    update pp_order_head
    set pp_order_head_id = #{record.ppOrderHeadId,jdbcType=INTEGER},
      seller_crm = #{record.sellerCrm,jdbcType=VARCHAR},
      buyer_name = #{record.buyerName,jdbcType=VARCHAR},
      buyer_uin = #{record.buyerUin,jdbcType=VARCHAR},
      buyer_remark = #{record.buyerRemark,jdbcType=VARCHAR},
      combo_info = #{record.comboInfo,jdbcType=VARCHAR},
      deal_code = #{record.dealCode,jdbcType=VARCHAR},
      deal_desc = #{record.dealDesc,jdbcType=VARCHAR},
      deal_detail_link = #{record.dealDetailLink,jdbcType=VARCHAR},
      deal_note_type = #{record.dealNoteType,jdbcType=VARCHAR},
      deal_note = #{record.dealNote,jdbcType=VARCHAR},
      deal_state = #{record.dealState,jdbcType=VARCHAR},
      deal_state_desc = #{record.dealStateDesc,jdbcType=VARCHAR},
      property_mask = #{record.propertyMask,jdbcType=VARCHAR},
      deal_type = #{record.dealType,jdbcType=VARCHAR},
      deal_type_desc = #{record.dealTypeDesc,jdbcType=VARCHAR},
      deal_pay_type = #{record.dealPayType,jdbcType=VARCHAR},
      deal_pay_type_desc = #{record.dealPayTypeDesc,jdbcType=VARCHAR},
      deal_rate_state = #{record.dealRateState,jdbcType=VARCHAR},
      deal_rate_state_desc = #{record.dealRateStateDesc,jdbcType=VARCHAR},
      create_time = #{record.createTime,jdbcType=TIMESTAMP},
      deal_end_time = #{record.dealEndTime,jdbcType=TIMESTAMP},
      last_update_time = #{record.lastUpdateTime,jdbcType=TIMESTAMP},
      pay_time = #{record.payTime,jdbcType=TIMESTAMP},
      pay_return_time = #{record.payReturnTime,jdbcType=TIMESTAMP},
      recvfee_return_time = #{record.recvfeeReturnTime,jdbcType=TIMESTAMP},
      recvfee_time = #{record.recvfeeTime,jdbcType=TIMESTAMP},
      seller_consignment_time = #{record.sellerConsignmentTime,jdbcType=TIMESTAMP},
      has_invoice = #{record.hasInvoice,jdbcType=INTEGER},
      invoice_content = #{record.invoiceContent,jdbcType=VARCHAR},
      invoice_title = #{record.invoiceTitle,jdbcType=VARCHAR},
      tenpay_code = #{record.tenpayCode,jdbcType=VARCHAR},
      transport_type = #{record.transportType,jdbcType=VARCHAR},
      transport_type_desc = #{record.transportTypeDesc,jdbcType=VARCHAR},
      who_pay_shippingfee = #{record.whoPayShippingfee,jdbcType=INTEGER},
      wuliu_id = #{record.wuliuId,jdbcType=VARCHAR},
      receiver_address = #{record.receiverAddress,jdbcType=VARCHAR},
      receiver_mobile = #{record.receiverMobile,jdbcType=VARCHAR},
      receiver_name = #{record.receiverName,jdbcType=VARCHAR},
      receiver_phone = #{record.receiverPhone,jdbcType=VARCHAR},
      receiver_postcode = #{record.receiverPostcode,jdbcType=VARCHAR},
      seller_recv_refund = #{record.sellerRecvRefund,jdbcType=DECIMAL},
      buyer_recv_refund = #{record.buyerRecvRefund,jdbcType=DECIMAL},
      coupon_fee = #{record.couponFee,jdbcType=DECIMAL},
      deal_pay_fee_point = #{record.dealPayFeePoint,jdbcType=DECIMAL},
      deal_pay_fee_ticket = #{record.dealPayFeeTicket,jdbcType=DECIMAL},
      deal_pay_fee_total = #{record.dealPayFeeTotal,jdbcType=DECIMAL},
      freight = #{record.freight,jdbcType=DECIMAL},
      shippingfee_calc = #{record.shippingfeeCalc,jdbcType=DECIMAL},
      total_cash = #{record.totalCash,jdbcType=DECIMAL},
      seller_name = #{record.sellerName,jdbcType=VARCHAR},
      seller_uin = #{record.sellerUin,jdbcType=VARCHAR},
      expect_arrival_time = #{record.expectArrivalTime,jdbcType=TIMESTAMP},
      store_id = #{record.storeId,jdbcType=INTEGER},
      update_time = #{record.updateTime,jdbcType=TIMESTAMP},
      update_flag = #{record.updateFlag,jdbcType=VARCHAR}
    <if test="_parameter != null" >
      <include refid="Update_By_Example_Where_Clause" />
    </if>
  </update>
  <update id="updateByPrimaryKeySelective" parameterType="com.sunmw.paipai.domain.PpOrderHead" >
    <!--
      WARNING - @mbggenerated
      This element is automatically generated by MyBatis Generator, do not modify.
    -->
    update pp_order_head
    <set >
      <if test="sellerCrm != null" >
        seller_crm = #{sellerCrm,jdbcType=VARCHAR},
      </if>
      <if test="buyerName != null" >
        buyer_name = #{buyerName,jdbcType=VARCHAR},
      </if>
      <if test="buyerUin != null" >
        buyer_uin = #{buyerUin,jdbcType=VARCHAR},
      </if>
      <if test="buyerRemark != null" >
        buyer_remark = #{buyerRemark,jdbcType=VARCHAR},
      </if>
      <if test="comboInfo != null" >
        combo_info = #{comboInfo,jdbcType=VARCHAR},
      </if>
      <if test="dealCode != null" >
        deal_code = #{dealCode,jdbcType=VARCHAR},
      </if>
      <if test="dealDesc != null" >
        deal_desc = #{dealDesc,jdbcType=VARCHAR},
      </if>
      <if test="dealDetailLink != null" >
        deal_detail_link = #{dealDetailLink,jdbcType=VARCHAR},
      </if>
      <if test="dealNoteType != null" >
        deal_note_type = #{dealNoteType,jdbcType=VARCHAR},
      </if>
      <if test="dealNote != null" >
        deal_note = #{dealNote,jdbcType=VARCHAR},
      </if>
      <if test="dealState != null" >
        deal_state = #{dealState,jdbcType=VARCHAR},
      </if>
      <if test="dealStateDesc != null" >
        deal_state_desc = #{dealStateDesc,jdbcType=VARCHAR},
      </if>
      <if test="propertyMask != null" >
        property_mask = #{propertyMask,jdbcType=VARCHAR},
      </if>
      <if test="dealType != null" >
        deal_type = #{dealType,jdbcType=VARCHAR},
      </if>
      <if test="dealTypeDesc != null" >
        deal_type_desc = #{dealTypeDesc,jdbcType=VARCHAR},
      </if>
      <if test="dealPayType != null" >
        deal_pay_type = #{dealPayType,jdbcType=VARCHAR},
      </if>
      <if test="dealPayTypeDesc != null" >
        deal_pay_type_desc = #{dealPayTypeDesc,jdbcType=VARCHAR},
      </if>
      <if test="dealRateState != null" >
        deal_rate_state = #{dealRateState,jdbcType=VARCHAR},
      </if>
      <if test="dealRateStateDesc != null" >
        deal_rate_state_desc = #{dealRateStateDesc,jdbcType=VARCHAR},
      </if>
      <if test="createTime != null" >
        create_time = #{createTime,jdbcType=TIMESTAMP},
      </if>
      <if test="dealEndTime != null" >
        deal_end_time = #{dealEndTime,jdbcType=TIMESTAMP},
      </if>
      <if test="lastUpdateTime != null" >
        last_update_time = #{lastUpdateTime,jdbcType=TIMESTAMP},
      </if>
      <if test="payTime != null" >
        pay_time = #{payTime,jdbcType=TIMESTAMP},
      </if>
      <if test="payReturnTime != null" >
        pay_return_time = #{payReturnTime,jdbcType=TIMESTAMP},
      </if>
      <if test="recvfeeReturnTime != null" >
        recvfee_return_time = #{recvfeeReturnTime,jdbcType=TIMESTAMP},
      </if>
      <if test="recvfeeTime != null" >
        recvfee_time = #{recvfeeTime,jdbcType=TIMESTAMP},
      </if>
      <if test="sellerConsignmentTime != null" >
        seller_consignment_time = #{sellerConsignmentTime,jdbcType=TIMESTAMP},
      </if>
      <if test="hasInvoice != null" >
        has_invoice = #{hasInvoice,jdbcType=INTEGER},
      </if>
      <if test="invoiceContent != null" >
        invoice_content = #{invoiceContent,jdbcType=VARCHAR},
      </if>
      <if test="invoiceTitle != null" >
        invoice_title = #{invoiceTitle,jdbcType=VARCHAR},
      </if>
      <if test="tenpayCode != null" >
        tenpay_code = #{tenpayCode,jdbcType=VARCHAR},
      </if>
      <if test="transportType != null" >
        transport_type = #{transportType,jdbcType=VARCHAR},
      </if>
      <if test="transportTypeDesc != null" >
        transport_type_desc = #{transportTypeDesc,jdbcType=VARCHAR},
      </if>
      <if test="whoPayShippingfee != null" >
        who_pay_shippingfee = #{whoPayShippingfee,jdbcType=INTEGER},
      </if>
      <if test="wuliuId != null" >
        wuliu_id = #{wuliuId,jdbcType=VARCHAR},
      </if>
      <if test="receiverAddress != null" >
        receiver_address = #{receiverAddress,jdbcType=VARCHAR},
      </if>
      <if test="receiverMobile != null" >
        receiver_mobile = #{receiverMobile,jdbcType=VARCHAR},
      </if>
      <if test="receiverName != null" >
        receiver_name = #{receiverName,jdbcType=VARCHAR},
      </if>
      <if test="receiverPhone != null" >
        receiver_phone = #{receiverPhone,jdbcType=VARCHAR},
      </if>
      <if test="receiverPostcode != null" >
        receiver_postcode = #{receiverPostcode,jdbcType=VARCHAR},
      </if>
      <if test="sellerRecvRefund != null" >
        seller_recv_refund = #{sellerRecvRefund,jdbcType=DECIMAL},
      </if>
      <if test="buyerRecvRefund != null" >
        buyer_recv_refund = #{buyerRecvRefund,jdbcType=DECIMAL},
      </if>
      <if test="couponFee != null" >
        coupon_fee = #{couponFee,jdbcType=DECIMAL},
      </if>
      <if test="dealPayFeePoint != null" >
        deal_pay_fee_point = #{dealPayFeePoint,jdbcType=DECIMAL},
      </if>
      <if test="dealPayFeeTicket != null" >
        deal_pay_fee_ticket = #{dealPayFeeTicket,jdbcType=DECIMAL},
      </if>
      <if test="dealPayFeeTotal != null" >
        deal_pay_fee_total = #{dealPayFeeTotal,jdbcType=DECIMAL},
      </if>
      <if test="freight != null" >
        freight = #{freight,jdbcType=DECIMAL},
      </if>
      <if test="shippingfeeCalc != null" >
        shippingfee_calc = #{shippingfeeCalc,jdbcType=DECIMAL},
      </if>
      <if test="totalCash != null" >
        total_cash = #{totalCash,jdbcType=DECIMAL},
      </if>
      <if test="sellerName != null" >
        seller_name = #{sellerName,jdbcType=VARCHAR},
      </if>
      <if test="sellerUin != null" >
        seller_uin = #{sellerUin,jdbcType=VARCHAR},
      </if>
      <if test="expectArrivalTime != null" >
        expect_arrival_time = #{expectArrivalTime,jdbcType=TIMESTAMP},
      </if>
      <if test="storeId != null" >
        store_id = #{storeId,jdbcType=INTEGER},
      </if>
      <if test="updateTime != null" >
        update_time = #{updateTime,jdbcType=TIMESTAMP},
      </if>
      <if test="updateFlag != null" >
        update_flag = #{updateFlag,jdbcType=VARCHAR},
      </if>
    </set>
    where pp_order_head_id = #{ppOrderHeadId,jdbcType=INTEGER}
  </update>
  <update id="updateByPrimaryKey" parameterType="com.sunmw.paipai.domain.PpOrderHead" >
    <!--
      WARNING - @mbggenerated
      This element is automatically generated by MyBatis Generator, do not modify.
    -->
    update pp_order_head
    set seller_crm = #{sellerCrm,jdbcType=VARCHAR},
      buyer_name = #{buyerName,jdbcType=VARCHAR},
      buyer_uin = #{buyerUin,jdbcType=VARCHAR},
      buyer_remark = #{buyerRemark,jdbcType=VARCHAR},
      combo_info = #{comboInfo,jdbcType=VARCHAR},
      deal_code = #{dealCode,jdbcType=VARCHAR},
      deal_desc = #{dealDesc,jdbcType=VARCHAR},
      deal_detail_link = #{dealDetailLink,jdbcType=VARCHAR},
      deal_note_type = #{dealNoteType,jdbcType=VARCHAR},
      deal_note = #{dealNote,jdbcType=VARCHAR},
      deal_state = #{dealState,jdbcType=VARCHAR},
      deal_state_desc = #{dealStateDesc,jdbcType=VARCHAR},
      property_mask = #{propertyMask,jdbcType=VARCHAR},
      deal_type = #{dealType,jdbcType=VARCHAR},
      deal_type_desc = #{dealTypeDesc,jdbcType=VARCHAR},
      deal_pay_type = #{dealPayType,jdbcType=VARCHAR},
      deal_pay_type_desc = #{dealPayTypeDesc,jdbcType=VARCHAR},
      deal_rate_state = #{dealRateState,jdbcType=VARCHAR},
      deal_rate_state_desc = #{dealRateStateDesc,jdbcType=VARCHAR},
      create_time = #{createTime,jdbcType=TIMESTAMP},
      deal_end_time = #{dealEndTime,jdbcType=TIMESTAMP},
      last_update_time = #{lastUpdateTime,jdbcType=TIMESTAMP},
      pay_time = #{payTime,jdbcType=TIMESTAMP},
      pay_return_time = #{payReturnTime,jdbcType=TIMESTAMP},
      recvfee_return_time = #{recvfeeReturnTime,jdbcType=TIMESTAMP},
      recvfee_time = #{recvfeeTime,jdbcType=TIMESTAMP},
      seller_consignment_time = #{sellerConsignmentTime,jdbcType=TIMESTAMP},
      has_invoice = #{hasInvoice,jdbcType=INTEGER},
      invoice_content = #{invoiceContent,jdbcType=VARCHAR},
      invoice_title = #{invoiceTitle,jdbcType=VARCHAR},
      tenpay_code = #{tenpayCode,jdbcType=VARCHAR},
      transport_type = #{transportType,jdbcType=VARCHAR},
      transport_type_desc = #{transportTypeDesc,jdbcType=VARCHAR},
      who_pay_shippingfee = #{whoPayShippingfee,jdbcType=INTEGER},
      wuliu_id = #{wuliuId,jdbcType=VARCHAR},
      receiver_address = #{receiverAddress,jdbcType=VARCHAR},
      receiver_mobile = #{receiverMobile,jdbcType=VARCHAR},
      receiver_name = #{receiverName,jdbcType=VARCHAR},
      receiver_phone = #{receiverPhone,jdbcType=VARCHAR},
      receiver_postcode = #{receiverPostcode,jdbcType=VARCHAR},
      seller_recv_refund = #{sellerRecvRefund,jdbcType=DECIMAL},
      buyer_recv_refund = #{buyerRecvRefund,jdbcType=DECIMAL},
      coupon_fee = #{couponFee,jdbcType=DECIMAL},
      deal_pay_fee_point = #{dealPayFeePoint,jdbcType=DECIMAL},
      deal_pay_fee_ticket = #{dealPayFeeTicket,jdbcType=DECIMAL},
      deal_pay_fee_total = #{dealPayFeeTotal,jdbcType=DECIMAL},
      freight = #{freight,jdbcType=DECIMAL},
      shippingfee_calc = #{shippingfeeCalc,jdbcType=DECIMAL},
      total_cash = #{totalCash,jdbcType=DECIMAL},
      seller_name = #{sellerName,jdbcType=VARCHAR},
      seller_uin = #{sellerUin,jdbcType=VARCHAR},
      expect_arrival_time = #{expectArrivalTime,jdbcType=TIMESTAMP},
      store_id = #{storeId,jdbcType=INTEGER},
      update_time = #{updateTime,jdbcType=TIMESTAMP},
      update_flag = #{updateFlag,jdbcType=VARCHAR}
    where pp_order_head_id = #{ppOrderHeadId,jdbcType=INTEGER}
  </update>
</mapper>